texttv/__init__.py
texttv/texttv.py
texttv-0.1.dist-info/LICENSE
texttv-0.1.dist-info/METADATA
texttv-0.1.dist-info/WHEEL
texttv-0.1.dist-info/entry_points.txt
texttv-0.1.dist-info/top_level.txt
texttv-0.1.dist-info/RECORD
