Metadata-Version: 2.1
Name: texttv
Version: 0.1
Summary: A terminal SVT Text TV client
Home-page: https://github.com/erikstenlund/texttv
Author: Erik Stenlund
Author-email: erikstenlund@protonmail.com
License: MIT
Platform: UNKNOWN
License-File: LICENSE
Requires-Dist: readchar
